odoo/addons/l10n_it_fatturapa_import_zip/README.rst
odoo/addons/l10n_it_fatturapa_import_zip/__init__.py
odoo/addons/l10n_it_fatturapa_import_zip/__manifest__.py
odoo/addons/l10n_it_fatturapa_import_zip/i18n/it.po
odoo/addons/l10n_it_fatturapa_import_zip/i18n/l10n_it_fatturapa_import_zip.pot
odoo/addons/l10n_it_fatturapa_import_zip/migrations/14.0.1.1.0/post-migrate.py
odoo/addons/l10n_it_fatturapa_import_zip/models/__init__.py
odoo/addons/l10n_it_fatturapa_import_zip/models/account_invoice.py
odoo/addons/l10n_it_fatturapa_import_zip/models/attachment.py
odoo/addons/l10n_it_fatturapa_import_zip/readme/CONTRIBUTORS.rst
odoo/addons/l10n_it_fatturapa_import_zip/readme/DESCRIPTION.rst
odoo/addons/l10n_it_fatturapa_import_zip/readme/USAGE.rst
odoo/addons/l10n_it_fatturapa_import_zip/security/ir.model.access.csv
odoo/addons/l10n_it_fatturapa_import_zip/security/rules.xml
odoo/addons/l10n_it_fatturapa_import_zip/static/description/icon.png
odoo/addons/l10n_it_fatturapa_import_zip/static/description/index.html
odoo/addons/l10n_it_fatturapa_import_zip/tests/__init__.py
odoo/addons/l10n_it_fatturapa_import_zip/tests/test_import_zip.py
odoo/addons/l10n_it_fatturapa_import_zip/tests/data/xml_import.zip
odoo/addons/l10n_it_fatturapa_import_zip/views/account_invoice_views.xml
odoo/addons/l10n_it_fatturapa_import_zip/views/attachment_views.xml
odoo/addons/l10n_it_fatturapa_import_zip/wizards/__init__.py
odoo/addons/l10n_it_fatturapa_import_zip/wizards/wizard_import_fatturapa.py
odoo14_addon_l10n_it_fatturapa_import_zip-14.0.1.1.1.dist-info/METADATA
odoo14_addon_l10n_it_fatturapa_import_zip-14.0.1.1.1.dist-info/WHEEL
odoo14_addon_l10n_it_fatturapa_import_zip-14.0.1.1.1.dist-info/top_level.txt
odoo14_addon_l10n_it_fatturapa_import_zip-14.0.1.1.1.dist-info/RECORD
