Metadata-Version: 2.1
Name: odoo14-addon-l10n_it_fatturapa_import_zip
Version: 14.0.1.1.1
Summary: Permette di importare in uno ZIP diversi file XML di fatture elettroniche
Home-page: https://github.com/OCA/l10n-italy
Author: TAKOBI, Odoo Community Association (OCA)
Author-email: support@odoo-community.org
License: AGPL-3
Classifier: Programming Language :: Python
Classifier: Framework :: Odoo
Classifier: Framework :: Odoo :: 14.0
Classifier: License :: OSI Approved :: GNU Affero General Public License v3
Requires-Python: >=3.6
Requires-Dist: odoo14-addon-l10n-it-account
Requires-Dist: odoo14-addon-l10n-it-fatturapa-in
Requires-Dist: odoo14-addon-l10n-it-fatturapa-out
Requires-Dist: odoo14-addon-l10n-it-fiscal-document-type
Requires-Dist: odoo14-addon-l10n-it-withholding-tax-reason
Requires-Dist: odoo<14.1dev,>=14.0a
